{
  "shenyangPersonality": {
    "traits": [
      {
        "name": "豪爽实在",
        "description": "沈阳人说话办事直接爽快，不拐弯抹角，讲究实在",
        "score": 90
      },
      {
        "name": "幽默风趣",
        "description": "典型的东北式幽默，喜欢开玩笑，语言生动有趣",
        "score": 85
      },
      {
        "name": "怀旧重情",
        "description": "对历史有深厚感情，重视传统，重情重义",
        "score": 88
      },
      {
        "name": "开放进取",
        "description": "积极接受新事物，有开拓精神，渴望发展",
        "score": 82
      },
      {
        "name": "工业精神",
        "description": "严谨、务实、注重效率，继承共和国长子的工业传统",
        "score": 92
      }
    ],
    "languageFeatures": {
      "pronunciation": "平翘舌不分，r音发y音，声调较平",
      "vocabulary": [
        "嘎哈（干什么）",
        "嗯呐（是的）",
        "唠嗑（聊天）",
        "杠杠的（很好）",
        "麻溜的（快点）",
        "膈应（讨厌）",
        "整点（喝点酒）",
        "秃噜（失败）",
        "波棱盖（膝盖）",
        "马路牙子（路缘）"
      ],
      "sentencePatterns": [
        "动词+啥：吃啥、喝啥、看啥",
        "老+形容词：老好了、老大了、老远了",
        "可+形容词+了：可好了、可大了、可远了"
      ]
    }
  },
  "historicalFacts": [
    {
      "era": "古代",
      "facts": [
        "沈阳有2300年建城史，战国时期属燕国辽东郡",
        "1625年，清太祖努尔哈赤迁都沈阳，1634年皇太极改沈阳为盛京",
        "1644年清军入关后，沈阳作为陪都保留宫殿和皇陵"
      ]
    },
    {
      "era": "近代",
      "facts": [
        "1898年，沙俄修建中东铁路南满支线，沈阳开始近代化",
        "1905年日俄战争后，日本获得南满铁路权益，沈阳成为日俄势力交汇点",
        "1923年设立奉天市政公所，沈阳成为中国最早建市的城市之一"
      ]
    },
    {
      "era": "现代",
      "facts": [
        "1948年辽沈战役胜利，沈阳解放",
        "1949年后，沈阳成为国家重点建设的工业基地，有'共和国长子'之称",
        "1986年国务院批准沈阳为国家历史文化名城"
      ]
    }
  ],
  "internationalAchievements": [
    {
      "category": "经贸合作",
      "items": [
        "中德（沈阳）高端装备制造产业园（2015年启动）",
        "中国（辽宁）自由贸易试验区沈阳片区（2017年挂牌）",
        "沈阳综合保税区（2011年封关运行）"
      ]
    },
    {
      "category": "文化交流",
      "items": [
        "沈阳国际马拉松（2015年首次举办）",
        "中国沈阳国际旅游节（每年举办）",
        "沈阳国际友好活动月（促进民间外交）"
      ]
    },
    {
      "category": "城市外交",
      "items": [
        "友好城市：德国杜塞尔多夫、日本札幌、韩国大田、美国芝加哥等23个",
        "友好合作关系城市：法国里昂、俄罗斯伊尔库茨克等14个",
        "驻沈领事机构：美国、日本、韩国、法国、德国、俄罗斯、朝鲜总领事馆"
      ]
    }
  ]
}